quadfitmodule.cp311-win_amd64.pyd
quadfit/__init__.py
quadfit/quadfit.py
quadfit/quadfitmodule.c
quadfit-1.1.0.dist-info/licenses/LICENSE
quadfit-1.1.0.dist-info/METADATA
quadfit-1.1.0.dist-info/WHEEL
quadfit-1.1.0.dist-info/top_level.txt
quadfit-1.1.0.dist-info/RECORD
