Metadata-Version: 2.4
Name: quadfit
Version: 1.1.0
Summary: Fork of QuadrilateralFitter rewritten in C. QuadrilateralFitter is an efficient and easy-to-use Python library for fitting irregular quadrilaterals from irregular polygons or any noisy data.
Author-email: Krzysztof Mizgała <krzysztof@mizgala.pl>
License-Expression: MIT
Project-URL: Homepage, https://github.com/KMChris/quadfit
Keywords: quadrilateral,fitter,polygon,shape analysis,geometry
Classifier: Development Status :: 5 - Production/Stable
Classifier: Programming Language :: Python
Classifier: Programming Language :: Python :: 3
Classifier: Programming Language :: Python :: 3 :: Only
Classifier: Programming Language :: C
Classifier: Operating System :: OS Independent
Classifier: Intended Audience :: Developers
Classifier: Intended Audience :: Science/Research
Classifier: Intended Audience :: Education
Classifier: Topic :: Software Development :: Libraries
Classifier: Topic :: Software Development :: Libraries :: Python Modules
Classifier: Topic :: Scientific/Engineering :: Mathematics
Requires-Python: >=3.9
License-File: LICENSE
Requires-Dist: numpy
Dynamic: license-file
